remote_cmder/__init__.py
remote_cmder/__main__.py
remote_cmder/cli.py
remote_cmder/core/__init__.py
remote_cmder/core/enums.py
remote_cmder/modules/__init__.py
remote_cmder/modules/cmder.py
remote_cmder/modules/server.py
remote_cmder/settings/__init__.py
remote_cmder/settings/logger.py
remote_cmder/settings/storage.py
remote_cmder-0.0.7.dist-info/LICENSE
remote_cmder-0.0.7.dist-info/METADATA
remote_cmder-0.0.7.dist-info/WHEEL
remote_cmder-0.0.7.dist-info/entry_points.txt
remote_cmder-0.0.7.dist-info/top_level.txt
remote_cmder-0.0.7.dist-info/RECORD
