Metadata-Version: 2.1
Name: remote-cmder
Version: 0.0.7
Summary: Remote cmder
Home-page: https://github.com/zondatw/remote_cmder
Author: Zonda Yang
Author-email: u226699@gmail.com
License: MIT
Keywords: remote cmder
Classifier: Programming Language :: Python :: 3
Classifier: License :: OSI Approved :: MIT License
Requires-Python: >=3.7
License-File: LICENSE
